pulumi_keycloak/__init__.py
pulumi_keycloak/_inputs.py
pulumi_keycloak/_utilities.py
pulumi_keycloak/attribute_importer_identity_provider_mapper.py
pulumi_keycloak/attribute_to_role_identity_mapper.py
pulumi_keycloak/custom_identity_provider_mapping.py
pulumi_keycloak/custom_user_federation.py
pulumi_keycloak/default_groups.py
pulumi_keycloak/default_roles.py
pulumi_keycloak/generic_client_protocol_mapper.py
pulumi_keycloak/generic_client_role_mapper.py
pulumi_keycloak/generic_protocol_mapper.py
pulumi_keycloak/generic_role_mapper.py
pulumi_keycloak/get_authentication_execution.py
pulumi_keycloak/get_authentication_flow.py
pulumi_keycloak/get_client_description_converter.py
pulumi_keycloak/get_group.py
pulumi_keycloak/get_organization.py
pulumi_keycloak/get_realm.py
pulumi_keycloak/get_realm_keys.py
pulumi_keycloak/get_role.py
pulumi_keycloak/get_user.py
pulumi_keycloak/get_user_realm_roles.py
pulumi_keycloak/group.py
pulumi_keycloak/group_memberships.py
pulumi_keycloak/group_permissions.py
pulumi_keycloak/group_roles.py
pulumi_keycloak/hardcoded_attribute_identity_provider_mapper.py
pulumi_keycloak/hardcoded_attribute_mapper.py
pulumi_keycloak/hardcoded_group_identity_provider_mapper.py
pulumi_keycloak/hardcoded_role_identity_mapper.py
pulumi_keycloak/identity_provider_token_exchange_scope_permission.py
pulumi_keycloak/organization.py
pulumi_keycloak/outputs.py
pulumi_keycloak/provider.py
pulumi_keycloak/pulumi-plugin.json
pulumi_keycloak/py.typed
pulumi_keycloak/realm.py
pulumi_keycloak/realm_client_policy_profile.py
pulumi_keycloak/realm_client_policy_profile_policy.py
pulumi_keycloak/realm_default_client_scopes.py
pulumi_keycloak/realm_events.py
pulumi_keycloak/realm_keystore_aes_generated.py
pulumi_keycloak/realm_keystore_ecdsa_generated.py
pulumi_keycloak/realm_keystore_hmac_generated.py
pulumi_keycloak/realm_keystore_java_generated.py
pulumi_keycloak/realm_keystore_rsa.py
pulumi_keycloak/realm_keystore_rsa_generated.py
pulumi_keycloak/realm_localization.py
pulumi_keycloak-6.9.0.dist-info/METADATA
pulumi_keycloak-6.9.0.dist-info/WHEEL
pulumi_keycloak-6.9.0.dist-info/top_level.txt
pulumi_keycloak-6.9.0.dist-info/RECORD
